Workbook
Name Salario: 'Simulador FIIs'!$B$4
Name AporteSugestao: 'Simulador FIIs'!$B$5
Name AporteMensal: 'Simulador FIIs'!$B$6
Name TaxaMensal: 'Simulador FIIs'!$B$7
Name DYMensal: 'Simulador FIIs'!$B$8
Name PerfilInvestidor: 'Simulador FIIs'!$B$9
Name TabelaApoioPerfis: Apoio!$A$3:$E$20

Sheet Simulador FIIs
A1: FERRAMENTA DE SIMULAÇÃO E CONTROLE DE INVESTIMENTOS EM FIIs
A3: 1. PREMISSAS E PERGUNTAS DE NEGÓCIO | F3: 3. PROJEÇÃO DE CENÁRIOS E PATRIMÔNIO ACUMULADO (VF)
A4: Salário Mensal (R$) | B4: 5000 | F4: Anos (2º) | G4: Meses | H4: Aporte Acumulado | I4: Patrimônio Acumulado (VF - 4º) | J4: Rendimento Total | K4: Dividendos Mensais (5º) | L4: Retorno % / Aporte
A5: Sugestão de Aporte (30% Salário) | B5: =B4*0.30 | F5: 2 | G5: =F5*12 | H5: =G5*AporteMensal | I5: =-FV(TaxaMensal, G5, AporteMensal) | J5: =I5-H5 | K5: =I5*DYMensal | L5: =(I5-H5)/H5
A6: Quanto investir por mês? (Aporte Mensal) | B6: =B5 | F6: 5 | G6: =F6*12 | H6: =G6*AporteMensal | I6: =-FV(TaxaMensal, G6, AporteMensal) | J6: =I6-H6 | K6: =I6*DYMensal | L6: =(I6-H6)/H6
A7: Qual a taxa de rendimento mensal? (%) | B7: 0.008 | F7: 10 | G7: =F7*12 | H7: =G7*AporteMensal | I7: =-FV(TaxaMensal, G7, AporteMensal) | J7: =I7-H7 | K7: =I7*DYMensal | L7: =(I7-H7)/H7
A8: Dividend Yield Mensal (%) | B8: 0.0075 | F8: 15 | G8: =F8*12 | H8: =G8*AporteMensal | I8: =-FV(TaxaMensal, G8, AporteMensal) | J8: =I8-H8 | K8: =I8*DYMensal | L8: =(I8-H8)/H8
A9: Perfil do Investidor | B9: Moderado | F9: 20 | G9: =F9*12 | H9: =G9*AporteMensal | I9: =-FV(TaxaMensal, G9, AporteMensal) | J9: =I9-H9 | K9: =I9*DYMensal | L9: =(I9-H9)/H9
F10: 25 | G10: =F10*12 | H10: =G10*AporteMensal | I10: =-FV(TaxaMensal, G10, AporteMensal) | J10: =I10-H10 | K10: =I10*DYMensal | L10: =(I10-H10)/H10
A11: 2. DIVISÃO DO APORTE POR PERFIL (6 TIPOS DE FII) | F11: 30 | G11: =F11*12 | H11: =G11*AporteMensal | I11: =-FV(TaxaMensal, G11, AporteMensal) | J11: =I11-H11 | K11: =I11*DYMensal | L11: =(I11-H11)/H11
A12: Tipo de Fundo | B12: % Alocação | C12: Aporte Mensal (R$) | D12: Chave Composta
A13: FII Tijolo - Logística | B13: =VLOOKUP(D13, Apoio!$C$3:$E$20, 2, FALSE) | C13: =B13*AporteMensal | D13: =PerfilInvestidor&A13
A14: FII Tijolo - Renda Urbana | B14: =VLOOKUP(D14, Apoio!$C$3:$E$20, 2, FALSE) | C14: =B14*AporteMensal | D14: =PerfilInvestidor&A14
A15: FII Papel - CRI High Grade | B15: =VLOOKUP(D15, Apoio!$C$3:$E$20, 2, FALSE) | C15: =B15*AporteMensal | D15: =PerfilInvestidor&A15
A16: FII Papel - Recebíveis | B16: =VLOOKUP(D16, Apoio!$C$3:$E$20, 2, FALSE) | C16: =B16*AporteMensal | D16: =PerfilInvestidor&A16
A17: Fiagro - Crédito Agro | B17: =VLOOKUP(D17, Apoio!$C$3:$E$20, 2, FALSE) | C17: =B17*AporteMensal | D17: =PerfilInvestidor&A17
A18: FoFs - Fundos de Fundos | B18: =VLOOKUP(D18, Apoio!$C$3:$E$20, 2, FALSE) | C18: =B18*AporteMensal | D18: =PerfilInvestidor&A18
A19: TOTAL ALOCADO | B19: =SUM(B13:B18) | C19: =SUM(C13:C18)

Sheet Apoio
A1: TABELA DE APOIO - PERFIS E SEIS TIPOS DE FII | G1: Lista Perfis
A2: Perfil | B2: Tipo de Fundo | C2: Chave Composta | D2: % Alocação | E2: Aporte por Perfil | G2: Conservador
A3: Conservador | B3: FII Tijolo - Logística | C3: =A3&B3 | D3: 0.3 | E3: =D3*AporteMensal | G3: Moderado
A4: Conservador | B4: FII Tijolo - Renda Urbana | C4: =A4&B4 | D4: 0.25 | E4: =D4*AporteMensal | G4: Arrojado
A5: Conservador | B5: FII Papel - CRI High Grade | C5: =A5&B5 | D5: 0.25 | E5: =D5*AporteMensal
A6: Conservador | B6: FII Papel - Recebíveis | C6: =A6&B6 | D6: 0.1 | E6: =D6*AporteMensal
A7: Conservador | B7: Fiagro - Crédito Agro | C7: =A7&B7 | D7: 0.05 | E7: =D7*AporteMensal
A8: Conservador | B8: FoFs - Fundos de Fundos | C8: =A8&B8 | D8: 0.05 | E8: =D8*AporteMensal
A9: Moderado | B9: FII Tijolo - Logística | C9: =A9&B9 | D9: 0.25 | E9: =D9*AporteMensal
A10: Moderado | B10: FII Tijolo - Renda Urbana | C10: =A10&B10 | D10: 0.2 | E10: =D10*AporteMensal
A11: Moderado | B11: FII Papel - CRI High Grade | C11: =A11&B11 | D11: 0.2 | E11: =D11*AporteMensal
A12: Moderado | B12: FII Papel - Recebíveis | C12: =A12&B12 | D12: 0.15 | E12: =D12*AporteMensal
A13: Moderado | B13: Fiagro - Crédito Agro | C13: =A13&B13 | D13: 0.1 | E13: =D13*AporteMensal
A14: Moderado | B14: FoFs - Fundos de Fundos | C14: =A14&B14 | D14: 0.1 | E14: =D14*AporteMensal
A15: Arrojado | B15: FII Tijolo - Logística | C15: =A15&B15 | D15: 0.15 | E15: =D15*AporteMensal
A16: Arrojado | B16: FII Tijolo - Renda Urbana | C16: =A16&B16 | D16: 0.15 | E16: =D16*AporteMensal
... A20: Arrojado | B20: FoFs - Fundos de Fundos | C20: =A20&B20 | D20: 0.15 | E20: =D20*AporteMensal
